<dc:title>The Mystery of the Poor</dc:title>
<dc:author>Dorothy Day</dc:author>
<dc:source>The Catholic Worker, April 1964, 2.</dc:source>
<dc:description>Answers students' question: "How can you see Christ in people?" Says Christ shows himself in the hands and feet of the poor around us. What we do for the poor we do for Christ which leads to an increase in faith and belief in love.</dc:description>
<dc:identifier>DDLW #189</dc:identifier>
<dc:date>1964-04-01</dc:date>
<dc:publisher>James Allaire</dc:publisher>
<dc:rights>Creative Commons Non-Commercial Share Alike 3.0</dc:rights>
<dc:language>en-US</dc:language>
<dc:relation>http://www.catholicworker.org/dorothyday/daytext.cfm?TextID=189</dc:relation>
