<dc:title>From Union Square to Rome<dc:title>
<dc:author>Dorothy Day</dc:author>
<dc:source>1938, Chapter 3, pp. 28-36.</dc:source>
<dc:description>Describes her sheltered childhood and her voluminous reading. After being baptized in the Episcopalian Church and loving the services she disavows organized religion as her sense of social justice developles.</dc:description>
<dc:identifier>DDLW #203</dc:identifier>
<dc:date>1938-01-05</dc:date>
<dc:publisher>James Allaire</dc:publisher>
<dc:rights>Creative Commons Non-Commercial Share Alike 3.0</dc:rights>
<dc:language>en-US</dc:language>
<dc:relation>http://www.catholicworker.org/dorothyday/daytext.cfm?TextID=203</dc:relation>
