<dc:title>Day After Day - January 1937</dc:title>
<dc:author>Dorothy Day</dc:author>
<dc:source>The Catholic Worker, January 1937, 4, 6.</dc:source>
<dc:description>Details about caring for workers during the seamens' strike--the need for large amounts of food, space to sleep, illness, high rent, and the threat of violence. Says unions need a supernatural outlook for "without a fatherhood of God, there can be no brotherhood of man."</dc:description>
<dc:identifier>DDLW #314</dc:identifier>
<dc:date>1937-01-02</dc:date>
<dc:publisher>James Allaire</dc:publisher>
<dc:rights>Creative Commons Non-Commercial Share Alike 3.0</dc:rights>
<dc:language>en-US</dc:language>
<dc:relation>http://www.catholicworker.org/dorothyday/daytext.cfm?TextID=314</dc:relation>
