<dc:title>On Pilgrimage - October 1947</dc:title>
<dc:author>Dorothy Day</dc:author>
<dc:source>The Catholic Worker, October 1847, 1, 2, 8.</dc:source>
<dc:description>Reflection on Peter Maurin's ideas of groups of farming families on the land. Notes the work Fall brings at the farm and describes the community life of Doukhobors, Shakers, and the extinct Ephrata Community. Dismisses the efficiency offered by advertising.</dc:description>
<dc:identifier>DDLW #459</dc:identifier>
<dc:date>1947-10-01</dc:date>
<dc:publisher>James Allaire</dc:publisher>
<dc:rights>Creative Commons Non-Commercial Share Alike 3.0</dc:rights>
<dc:language>en-US</dc:language>
<dc:relation>http://www.catholicworker.org/dorothyday/daytext.cfm?TextID=459</dc:relation>
