<dc:title>On Pilgrimage - July/August 1975</dc:title>
<dc:author>Dorothy Day</dc:author>
<dc:source>The Catholic Worker, July-August 1975, 2, 8.</dc:source>
<dc:description>Meandering reflections on joy in the midst of trouble, irritations mixed with beauty, peacemaking and resistance whilst threats of war persist. Invokes numerous Saints.</dc:description>
<dc:identifier>DDLW #553</dc:identifier>
<dc:date>1975-07-01</dc:date>
<dc:publisher>James Allaire</dc:publisher>
<dc:rights>Creative Commons Non-Commercial Share Alike 3.0</dc:rights>
<dc:language>en-US</dc:language>
<dc:relation>http://www.catholicworker.org/dorothyday/daytext.cfm?TextID=553</dc:relation>
