<dc:title>This Then is Perfect Joy</dc:title>
<dc:author>Dorothy Day</dc:author>
<dc:source>The Catholic Worker, June 1977, 8</dc:source>
<dc:description>A loving tribute to Peter Maurin--"another St. Francis of modern times." Praises his vision, his poverty, his holiness, and his teachings. Recalls the trial of Peter's last five years when his mind failed him.</dc:description>
<dc:identifier>DDLW #924</dc:identifier>
<dc:date>1977-06-01</dc:date>
<dc:publisher>James Allaire</dc:publisher>
<dc:rights>Creative Commons Non-Commercial Share Alike 3.0</dc:rights>
<dc:language>en-US</dc:language>
<dc:relation>http://www.catholicworker.org/dorothyday/daytext.cfm?TextID=924</dc:relation>
