<dc:title>On Pilgrimage - October 1955</dc:title>
<dc:author>Dorothy Day</dc:author>
<dc:source>The Catholic Worker, Oct 1955, p. 3</dc:source>
<dc:description>Anticipates the ordeal of her and others' appearance in court for disobeying the Civil Defense Act. They plead guilty. Visits migrant workers in southern Minnesota and describes their hard life. Praises the work of women for donations to the stricken of the world. Lauds the factory work in Chicago of the Little Sisters of Charles de Foucauld.</dc:description>
<dc:identifier>DDLW #929</dc:identifier>
<dc:date>1955-10-01</dc:date>
<dc:publisher>James Allaire</dc:publisher>
<dc:rights>Creative Commons Non-Commercial Share Alike 3.0</dc:rights>
<dc:language>en-US</dc:language>
<dc:relation>http://www.catholicworker.org/dorothyday/daytext.cfm?TextID=929</dc:relation>
